MANIFEST.in
README.rst
setup.py
kiddiepool/__init__.py
kiddiepool/client.py
kiddiepool/connection.py
kiddiepool/exceptions.py
kiddiepool/fake.py
kiddiepool/pool.py
kiddiepool.egg-info/PKG-INFO
kiddiepool.egg-info/SOURCES.txt
kiddiepool.egg-info/dependency_links.txt
kiddiepool.egg-info/requires.txt
kiddiepool.egg-info/top_level.txt
tests/__init__.py
tests/test_integration.py
tests/test_units.py