Metadata-Version: 1.0
Name: kiddiepool
Version: 1.0.2
Summary: An extensible driver framework with pooling
Home-page: https://github.com/urbanairship/kiddiepool
Author: Urban Airship
Author-email: platform@urbanairship.com
License: Apache
Platform: UNKNOWN
Classifier: License :: OSI Approved :: Apache Software License
